{
  "merchant": "Blinkit",
  "merchantId": "blinkit",
  "products": [
    { "id": "b1", "name": "Aashirvaad Atta", "category": "staples", "price": 295, "unit": "5kg", "inStock": true, "eta": 12 },
    { "id": "b2", "name": "Amul Toned Milk", "category": "dairy", "price": 30, "unit": "500ml", "inStock": true, "eta": 11 },
    { "id": "b3", "name": "Toor Dal", "category": "staples", "price": 155, "unit": "1kg", "inStock": true, "eta": 12 },
    { "id": "b4", "name": "Fortune Sunflower Oil", "category": "staples", "price": 152, "unit": "1L", "inStock": true, "eta": 13 },
    { "id": "b5", "name": "Britannia Bread", "category": "bakery", "price": 42, "unit": "400g", "inStock": true, "eta": 10 },
    { "id": "b7", "name": "Tata Sugar", "category": "staples", "price": 50, "unit": "1kg", "inStock": true, "eta": 12 },
    { "id": "b8", "name": "Tata Salt", "category": "staples", "price": 27, "unit": "1kg", "inStock": true, "eta": 11 },
    { "id": "b9", "name": "Tata Tea Gold", "category": "beverages", "price": 310, "unit": "500g", "inStock": true, "eta": 12 },
    { "id": "b10", "name": "Nescafe Classic Coffee", "category": "beverages", "price": 215, "unit": "100g", "inStock": true, "eta": 12 },
    { "id": "b11", "name": "Parle-G Biscuits", "category": "snacks", "price": 10, "unit": "80g", "inStock": true, "eta": 10 },
    { "id": "b12", "name": "Amul Dahi", "category": "dairy", "price": 38, "unit": "400g", "inStock": true, "eta": 11 },
    { "id": "b13", "name": "Amul Ghee", "category": "dairy", "price": 565, "unit": "1L", "inStock": true, "eta": 13 },
    { "id": "b14", "name": "India Gate Basmati Rice", "category": "staples", "price": 415, "unit": "5kg", "inStock": false, "eta": 0 },
    { "id": "b15", "name": "Amul Paneer", "category": "dairy", "price": 90, "unit": "200g", "inStock": true, "eta": 11 }
  ]
}
